<?xml version="1.0" standalone="no"?>
<!DOCTYPE class PUBLIC "-//UC Berkeley//DTD MoML 1//EN"
    "http://ptolemy.eecs.berkeley.edu/xml/dtd/MoML_1.dtd">
<class name="Generator" extends="ptolemy.actor.TypedCompositeActor">
    <property name="_createdBy" class="ptolemy.kernel.attributes.VersionAttribute" value="9.1.devel">
    </property>
    <!-- include jars needed by all the EPS models in case someone downloads one model and clicks the the next. --> <property name="_jnlpClassesToJars" class="ptolemy.data.expr.Parameter" value="{{&quot;ptolemy.data.expr.Parameterk&quot;,&quot;ptolemy/data/ontologies/ontologies.jar&quot;},{&quot;ptolemy.kernel.attributes.VersionAttribute&quot;,&quot;ptolemy/domains/de/de.jar&quot;},{&quot;ptolemy.kernel.util.StringAttribute&quot;,&quot;ptolemy/actor/lib/aspect/aspect.jar&quot;},{&quot;ptolemy.kernel.util.Location&quot;,&quot;ptolemy/domains/sdf/sdf.jar&quot;},{&quot;ptolemy.actor.gui.SizeAttribute&quot;,&quot;ptolemy/actor/lib/fmi/fmi.jar&quot;},{&quot;ptolemy.kernel.util.ColorAttribute&quot;,&quot;ptolemy/domains/ptides/ptides.jar&quot;}}"/>
    <property name="_location" class="ptolemy.kernel.util.Location" value="[500.0, 445.0]">
    </property>
    <property name="_windowProperties" class="ptolemy.actor.gui.WindowPropertiesAttribute" value="{bounds={393, 217, 1026, 673}, maximized=false}">
    </property>
    <property name="_vergilSize" class="ptolemy.actor.gui.SizeAttribute" value="[792, 563]">
    </property>
    <property name="_vergilZoomFactor" class="ptolemy.data.expr.ExpertParameter" value="1.1040202944907076">
    </property>
    <property name="_vergilCenter" class="ptolemy.data.expr.ExpertParameter" value="{307.037109375, 259.4482946371483}">
    </property>
    <property name="timeConstant" class="ptolemy.data.expr.Parameter" value="1.0">
        <property name="_hideName" class="ptolemy.kernel.util.SingletonAttribute">
        </property>
        <property name="_icon" class="ptolemy.vergil.icon.ValueIcon">
            <property name="_color" class="ptolemy.actor.gui.ColorAttribute" value="{0.0, 0.0, 1.0, 1.0}">
            </property>
        </property>
        <property name="_smallIconDescription" class="ptolemy.kernel.util.SingletonConfigurableAttribute">
            <configure>
      <svg>
        <text x="20" style="font-size:14; font-family:SansSerif; fill:blue" y="20">-P-</text>
      </svg>
    </configure>
        </property>
        <property name="_editorFactory" class="ptolemy.vergil.toolbox.VisibleParameterEditorFactory">
        </property>
        <property name="_location" class="ptolemy.kernel.util.Location" value="[-35.0, 20.0]">
        </property>
    </property>
    <property name="outputImpedance" class="ptolemy.data.expr.Parameter" value="1.0">
        <property name="_hideName" class="ptolemy.kernel.util.SingletonAttribute">
        </property>
        <property name="_icon" class="ptolemy.vergil.icon.ValueIcon">
            <property name="_color" class="ptolemy.actor.gui.ColorAttribute" value="{0.0, 0.0, 1.0, 1.0}">
            </property>
        </property>
        <property name="_smallIconDescription" class="ptolemy.kernel.util.SingletonConfigurableAttribute">
            <configure>
      <svg>
        <text x="20" style="font-size:14; font-family:SansSerif; fill:blue" y="20">-P-</text>
      </svg>
    </configure>
        </property>
        <property name="_editorFactory" class="ptolemy.vergil.toolbox.VisibleParameterEditorFactory">
        </property>
        <property name="_location" class="ptolemy.kernel.util.Location" value="[-35.0, 40.0]">
        </property>
    </property>
    <property name="Annotation" class="ptolemy.vergil.kernel.attributes.TextAttribute">
        <property name="textColor" class="ptolemy.actor.gui.ColorAttribute" value="{0.0,0.0,0.0,1.0}">
        </property>
        <property name="text" class="ptolemy.kernel.util.StringAttribute" value="Simple model of a generator with a first order continuous dynamics&#10;with the specified time constant. The output voltage will match the&#10;drive input if either the outputImpedance is zero or the load is absent&#10;or Infinity. This is a continuous-time model.">
        </property>
        <property name="_location" class="ptolemy.kernel.util.Location" value="[170.0, 5.0]">
        </property>
    </property>
    <property name="Annotation2" class="ptolemy.vergil.kernel.attributes.TextAttribute">
        <property name="textColor" class="ptolemy.actor.gui.ColorAttribute" value="{0.0,0.0,0.0,1.0}">
        </property>
        <property name="text" class="ptolemy.kernel.util.StringAttribute" value="If the load is absent, we interpret that&#10;as a load impedance of infinity.">
        </property>
        <property name="_location" class="ptolemy.kernel.util.Location" value="[10.0, 340.0]">
        </property>
    </property>
    <property name="enableBackwardTypeInference" class="ptolemy.data.expr.Parameter" value="false">
    </property>
    <property name="Annotation3" class="ptolemy.vergil.kernel.attributes.TextAttribute">
        <property name="textColor" class="ptolemy.actor.gui.ColorAttribute" value="{0.0,0.0,0.0,1.0}">
        </property>
        <property name="text" class="ptolemy.kernel.util.StringAttribute" value="Model here is a simple voltage divider.">
        </property>
        <property name="_location" class="ptolemy.kernel.util.Location" value="[170.0, 250.0]">
        </property>
    </property>
    <property name="Annotation4" class="ptolemy.vergil.kernel.attributes.TextAttribute">
        <property name="textColor" class="ptolemy.actor.gui.ColorAttribute" value="{1.0,0.0,0.0,1.0}">
        </property>
        <property name="text" class="ptolemy.kernel.util.StringAttribute" value="Note that this model could be easily elaborated with higher-order linear or nonlinear dynamics.">
        </property>
        <property name="_location" class="ptolemy.kernel.util.Location" value="[-40.0, 395.0]">
        </property>
    </property>
    <property name="Annotation5" class="ptolemy.vergil.kernel.attributes.TextAttribute">
        <property name="textColor" class="ptolemy.actor.gui.ColorAttribute" value="{0.0,0.0,0.0,1.0}">
        </property>
        <property name="text" class="ptolemy.kernel.util.StringAttribute" value="Limit the drive input.&#10;This is a simple example&#10;of a nonlinearity that a&#10;real generator might&#10;exhibit.">
        </property>
        <property name="_location" class="ptolemy.kernel.util.RelativeLocation" value="[-135.0, 30.0]">
            <property name="relativeTo" class="ptolemy.kernel.util.StringAttribute" value="Limiter">
            </property>
            <property name="relativeToElementName" class="ptolemy.kernel.util.StringAttribute" value="entity">
            </property>
        </property>
    </property>
    <property name="driveLimit" class="ptolemy.data.expr.Parameter" value="Infinity">
        <property name="_hideName" class="ptolemy.kernel.util.SingletonAttribute">
        </property>
        <property name="_icon" class="ptolemy.vergil.icon.ValueIcon">
            <property name="_color" class="ptolemy.actor.gui.ColorAttribute" value="{0.0, 0.0, 1.0, 1.0}">
            </property>
        </property>
        <property name="_smallIconDescription" class="ptolemy.kernel.util.SingletonConfigurableAttribute">
            <configure>
      <svg>
        <text x="20" style="font-size:14; font-family:SansSerif; fill:blue" y="20">-P-</text>
      </svg>
    </configure>
        </property>
        <property name="_editorFactory" class="ptolemy.vergil.toolbox.VisibleParameterEditorFactory">
        </property>
        <property name="_location" class="ptolemy.kernel.util.Location" value="[-35.0, 60.0]">
        </property>
    </property>
    <property name="Annotation6" class="ptolemy.vergil.kernel.attributes.TextAttribute">
        <property name="textColor" class="ptolemy.actor.gui.ColorAttribute" value="{0.0,0.0,0.0,1.0}">
        </property>
        <property name="text" class="ptolemy.kernel.util.StringAttribute" value="This loop is a simple&#10;example of linear model&#10;for the generator's response&#10;to the drive input.">
        </property>
        <property name="_location" class="ptolemy.kernel.util.Location" value="[420.0, 95.0]">
        </property>
    </property>
    <port name="drive" class="ptolemy.actor.TypedIOPort">
        <property name="input"/>
        <property name="_location" class="ptolemy.kernel.util.Location" value="[20.5, 120.0]">
        </property>
        <property name="_showName" class="ptolemy.data.expr.SingletonParameter" value="true">
        </property>
    </port>
    <port name="outputVoltage" class="ptolemy.actor.TypedIOPort">
        <property name="output"/>
        <property name="_location" class="ptolemy.kernel.util.Location" value="[595.0, 220.0]">
        </property>
        <property name="_showName" class="ptolemy.data.expr.SingletonParameter" value="true">
        </property>
    </port>
    <port name="load" class="ptolemy.actor.TypedIOPort">
        <property name="input"/>
        <property name="_location" class="ptolemy.kernel.util.Location" value="[20.0, 270.0]">
        </property>
        <property name="_showName" class="ptolemy.data.expr.SingletonParameter" value="true">
        </property>
    </port>
    <entity name="AddSubtract" class="ptolemy.actor.lib.AddSubtract">
        <property name="_location" class="ptolemy.kernel.util.Location" value="[182.25, 130.0]">
        </property>
    </entity>
    <entity name="Scale" class="ptolemy.actor.lib.Scale">
        <property name="factor" class="ptolemy.data.expr.Parameter" value="1.0/timeConstant">
        </property>
        <property name="_icon" class="ptolemy.vergil.icon.AttributeValueIcon">
            <property name="attributeName" class="ptolemy.kernel.util.StringAttribute" value="factor">
            </property>
        </property>
        <property name="_location" class="ptolemy.kernel.util.Location" value="[296.75, 130.0]">
        </property>
    </entity>
    <entity name="Integrator" class="ptolemy.domains.continuous.lib.Integrator">
        <property name="_location" class="ptolemy.kernel.util.Location" value="[372.25, 130.0]">
        </property>
    </entity>
    <entity name="Expression" class="ptolemy.actor.lib.Expression">
        <property name="expression" class="ptolemy.kernel.util.StringAttribute" value="(loadImpedance == Infinity) ? voltage&#10;: voltage*loadImpedance/(outputImpedance+loadImpedance)">
            <property name="style" class="ptolemy.actor.gui.style.TextStyle">
                <property name="height" class="ptolemy.data.expr.Parameter" value="10">
                </property>
                <property name="width" class="ptolemy.data.expr.Parameter" value="30">
                </property>
            </property>
        </property>
        <property name="_icon" class="ptolemy.vergil.icon.BoxedValueIcon">
            <property name="attributeName" class="ptolemy.kernel.util.StringAttribute" value="expression">
            </property>
            <property name="displayWidth" class="ptolemy.data.expr.Parameter" value="60">
            </property>
            <property name="displayHeight" class="ptolemy.data.expr.Parameter" value="10">
            </property>
        </property>
        <property name="_location" class="ptolemy.kernel.util.Location" value="[360.0, 220.0]">
        </property>
        <port name="voltage" class="ptolemy.actor.TypedIOPort">
            <property name="input"/>
            <property name="_showName" class="ptolemy.data.expr.SingletonParameter" value="true">
            </property>
        </port>
        <port name="loadImpedance" class="ptolemy.actor.TypedIOPort">
            <property name="input"/>
            <property name="_showName" class="ptolemy.data.expr.SingletonParameter" value="true">
            </property>
        </port>
    </entity>
    <entity name="Default" class="ptolemy.actor.lib.Default">
        <property name="_location" class="ptolemy.kernel.util.Location" value="[90.0, 270.0]">
        </property>
    </entity>
    <entity name="Const" class="ptolemy.actor.lib.Const">
        <property name="value" class="ptolemy.data.expr.Parameter" value="Infinity">
        </property>
        <doc>Create a constant sequence.</doc>
        <property name="_icon" class="ptolemy.vergil.icon.BoxedValueIcon">
            <property name="attributeName" class="ptolemy.kernel.util.StringAttribute" value="value">
            </property>
            <property name="displayWidth" class="ptolemy.data.expr.Parameter" value="60">
            </property>
        </property>
        <property name="_location" class="ptolemy.kernel.util.Location" value="{40, 325}">
        </property>
    </entity>
    <entity name="Limiter" class="ptolemy.actor.lib.Limiter">
        <property name="top" class="ptolemy.data.expr.Parameter" value="Infinity">
        </property>
        <property name="_location" class="ptolemy.kernel.util.Location" value="[90.0, 120.0]">
        </property>
    </entity>
    <relation name="relation5" class="ptolemy.actor.TypedIORelation">
        <property name="width" class="ptolemy.data.expr.Parameter" value="-1">
        </property>
        <vertex name="vertex1" value="[142.25, 175.0]">
        </vertex>
    </relation>
    <relation name="relation3" class="ptolemy.actor.TypedIORelation">
    </relation>
    <relation name="relation6" class="ptolemy.actor.TypedIORelation">
    </relation>
    <relation name="relation4" class="ptolemy.actor.TypedIORelation">
    </relation>
    <relation name="relation7" class="ptolemy.actor.TypedIORelation">
    </relation>
    <relation name="relation2" class="ptolemy.actor.TypedIORelation">
    </relation>
    <relation name="relation8" class="ptolemy.actor.TypedIORelation">
    </relation>
    <relation name="relation9" class="ptolemy.actor.TypedIORelation">
    </relation>
    <relation name="relation" class="ptolemy.actor.TypedIORelation">
    </relation>
    <link port="drive" relation="relation9"/>
    <link port="outputVoltage" relation="relation4"/>
    <link port="load" relation="relation7"/>
    <link port="AddSubtract.plus" relation="relation"/>
    <link port="AddSubtract.minus" relation="relation5"/>
    <link port="AddSubtract.output" relation="relation3"/>
    <link port="Scale.input" relation="relation3"/>
    <link port="Scale.output" relation="relation6"/>
    <link port="Integrator.derivative" relation="relation6"/>
    <link port="Integrator.state" relation="relation5"/>
    <link port="Expression.output" relation="relation4"/>
    <link port="Expression.voltage" relation="relation5"/>
    <link port="Expression.loadImpedance" relation="relation2"/>
    <link port="Default.preferred" relation="relation7"/>
    <link port="Default.alternate" relation="relation8"/>
    <link port="Default.output" relation="relation2"/>
    <link port="Const.output" relation="relation8"/>
    <link port="Limiter.input" relation="relation9"/>
    <link port="Limiter.output" relation="relation"/>
</class>
