<?xml version="1.0" standalone="no"?>
<!DOCTYPE entity PUBLIC "-//UC Berkeley//DTD MoML 1//EN"
    "http://ptolemy.eecs.berkeley.edu/xml/dtd/MoML_1.dtd">
<entity name="1Subscriber1PublisherNoInstanceClassName" class="ptolemy.actor.TypedCompositeActor">
    <property name="_createdBy" class="ptolemy.kernel.attributes.VersionAttribute" value="11.0.devel">
    </property>
    <property name="_windowProperties" class="ptolemy.actor.gui.WindowPropertiesAttribute" value="{bounds={51, 165, 931, 634}, maximized=true}">
    </property>
    <property name="_vergilSize" class="ptolemy.actor.gui.SizeAttribute" value="[697, 524]">
    </property>
    <property name="_vergilZoomFactor" class="ptolemy.data.expr.ExpertParameter" value="1.3749598355281203">
    </property>
    <property name="_vergilCenter" class="ptolemy.data.expr.ExpertParameter" value="{1233.825479351593, 900.9145507812501}">
    </property>
    <property name="enableBackwardTypeInference" class="ptolemy.data.expr.Parameter" value="false">
    </property>
    <property name="Annotation" class="ptolemy.vergil.kernel.attributes.TextAttribute">
        <property name="textSize" class="ptolemy.data.expr.Parameter" value="12">
        </property>
        <property name="textColor" class="ptolemy.actor.gui.ColorAttribute" value="{1.0,0.0,0.0,1.0}">
        </property>
        <property name="text" class="ptolemy.kernel.util.StringAttribute" value="PtolemyII - HLA/CERTI framework&#10;&#10;--------------------------------------------------------------&#10;Model Type: &#10;             Test - 1Subscriber1PublisherNoInstanceClassName&#10;&#10;Feature: &#10;             1 Federation with 2 federates &quot;Sender1&quot; and &quot;Receiver1&quot;&#10;             This federation is set to work out of the box.&#10;             However, if &quot;Name of HLA class instance&quot; in HlaSubscriber &#10;             and HlaPublisher do not match, then the following exception &#10;             is thrown:&#10;             &quot;The fire() method of this actor was never called. Usually, &#10;             this is an error indicating that starvation is occurring.&quot;&#10;----------------------------------------------------------------&#10;&#10;">
        </property>
        <property name="_location" class="ptolemy.kernel.util.Location" value="[980.0, 710.0]">
        </property>
    </property>
    <property name="Annotation3" class="ptolemy.vergil.kernel.attributes.TextAttribute">
        <property name="textColor" class="ptolemy.actor.gui.ColorAttribute" value="{0.2,0.2,0.2,1.0}">
        </property>
        <property name="text" class="ptolemy.kernel.util.StringAttribute" value="&#10;">
        </property>
        <property name="_location" class="ptolemy.kernel.util.Location" value="[990.0, 1070.0]">
        </property>
    </property>
    <property name="Annotation6" class="ptolemy.vergil.kernel.attributes.TextAttribute">
        <property name="textSize" class="ptolemy.data.expr.Parameter" value="14">
        </property>
        <property name="textColor" class="ptolemy.actor.gui.ColorAttribute" value="{0.0, 0.0, 1.0, 1.0}">
        </property>
        <property name="text" class="ptolemy.kernel.util.StringAttribute" value="Models:&#10;">
        </property>
        <property name="_location" class="ptolemy.kernel.util.Location" value="[982.0, 925.0]">
        </property>
    </property>
    <property name="Annotation5" class="ptolemy.vergil.kernel.attributes.TextAttribute">
        <property name="textSize" class="ptolemy.data.expr.Parameter" value="14">
        </property>
        <property name="text" class="ptolemy.kernel.util.StringAttribute" value="- Receiver 1">
        </property>
        <property name="_location" class="ptolemy.kernel.util.Location" value="{990.0, 945.0}">
        </property>
        <property name="LiveLink" class="ptolemy.actor.gui.LiveLink" value="Receiver1.xml">
            <property name="_hideName" class="ptolemy.kernel.util.SingletonAttribute">
            </property>
            <property name="_icon" class="ptolemy.vergil.icon.ValueIcon">
                <property name="_color" class="ptolemy.actor.gui.ColorAttribute" value="{0.0, 0.0, 1.0, 1.0}">
                </property>
            </property>
            <property name="_smallIconDescription" class="ptolemy.kernel.util.SingletonConfigurableAttribute">
                <configure>
      <svg>
        <text x="20" style="font-size:14; font-family:SansSerif; fill:blue" y="20">LL</text>
      </svg>
    </configure>
            </property>
            <property name="_editorFactory" class="ptolemy.vergil.toolbox.VisibleParameterEditorFactory">
            </property>
            <property name="_location" class="ptolemy.kernel.util.Location" value="{395, 280}">
            </property>
        </property>
        <property name="IconLink" class="ptolemy.vergil.basic.export.web.IconLink" value="http://ptolemy.eecs.berkeley.edu/ptolemyII/ptII11.0/ptII/org/hlacerti/test/auto/StaticMultiInstanceJoker/test001/DistributedSender1/index.html">
            <property name="linkTarget" class="ptolemy.vergil.basic.export.web.LinkTarget" value="_self">
            </property>
            <property name="_location" class="ptolemy.kernel.util.Location" value="{450, 180}">
            </property>
        </property>
    </property>
    <property name="Annotation4" class="ptolemy.vergil.kernel.attributes.TextAttribute">
        <property name="textSize" class="ptolemy.data.expr.Parameter" value="14">
        </property>
        <property name="text" class="ptolemy.kernel.util.StringAttribute" value="- Sender 1">
        </property>
        <property name="_location" class="ptolemy.kernel.util.Location" value="[990.0, 960.0]">
        </property>
        <property name="LiveLink" class="ptolemy.actor.gui.LiveLink" value="Sender1.xml">
            <property name="_hideName" class="ptolemy.kernel.util.SingletonAttribute">
            </property>
            <property name="_icon" class="ptolemy.vergil.icon.ValueIcon">
                <property name="_color" class="ptolemy.actor.gui.ColorAttribute" value="{0.0, 0.0, 1.0, 1.0}">
                </property>
            </property>
            <property name="_smallIconDescription" class="ptolemy.kernel.util.SingletonConfigurableAttribute">
                <configure>
      <svg>
        <text x="20" style="font-size:14; font-family:SansSerif; fill:blue" y="20">LL</text>
      </svg>
    </configure>
            </property>
            <property name="_editorFactory" class="ptolemy.vergil.toolbox.VisibleParameterEditorFactory">
            </property>
            <property name="_location" class="ptolemy.kernel.util.Location" value="{395, 280}">
            </property>
        </property>
        <property name="IconLink" class="ptolemy.vergil.basic.export.web.IconLink" value="http://ptolemy.eecs.berkeley.edu/ptolemyII/ptII11.0/ptII/org/hlacerti/test/auto/StaticMultiInstanceJoker/test001/DistributedSender1/index.html">
            <property name="linkTarget" class="ptolemy.vergil.basic.export.web.LinkTarget" value="_self">
            </property>
            <property name="_location" class="ptolemy.kernel.util.Location" value="{450, 180}">
            </property>
        </property>
    </property>
    <property name="Annotation2" class="ptolemy.vergil.kernel.attributes.TextAttribute">
        <property name="textSize" class="ptolemy.data.expr.Parameter" value="14">
        </property>
        <property name="textColor" class="ptolemy.actor.gui.ColorAttribute" value="{0.003921569,0.003921569,0.003921569,1.0}">
        </property>
        <property name="text" class="ptolemy.kernel.util.StringAttribute" value="Author: CIELE Ingenierie - http://www.ciele.fr">
        </property>
        <property name="_location" class="ptolemy.kernel.util.Location" value="[1020.0, 1070.0]">
        </property>
    </property>
    <property name="DE Director" class="ptolemy.domains.de.kernel.DEDirector">
        <property name="_location" class="ptolemy.kernel.util.Location" value="{1045.0, 1035.0}">
        </property>
    </property>
    <property name="Annotation7" class="ptolemy.vergil.kernel.attributes.TextAttribute">
        <property name="textSize" class="ptolemy.data.expr.Parameter" value="14">
        </property>
        <property name="textColor" class="ptolemy.actor.gui.ColorAttribute" value="{0.0, 0.0, 1.0, 1.0}">
        </property>
        <property name="text" class="ptolemy.kernel.util.StringAttribute" value="Automated execution:&#10;">
        </property>
        <property name="_location" class="ptolemy.kernel.util.Location" value="[980.0, 985.0]">
        </property>
    </property>
    <entity name="Sender1" class="ptolemy.vergil.actor.lib.VisualModelReference">
        <property name="modelFileOrURL" class="ptolemy.actor.parameters.FilePortParameter" value="Sender1.xml">
        </property>
        <property name="executionOnFiring" class="ptolemy.data.expr.StringParameter" value="run in a new thread">
        </property>
        <property name="lingerTime" class="ptolemy.data.expr.Parameter" value="100L">
        </property>
        <property name="spawnSeparateModels" class="ptolemy.data.expr.Parameter" value="false">
        </property>
        <property name="openOnFiring" class="ptolemy.data.expr.StringParameter" value="open in Vergil">
        </property>
        <property name="_location" class="ptolemy.kernel.util.Location" value="[1235.0, 1035.0]">
        </property>
    </entity>
    <entity name="Stop" class="ptolemy.actor.lib.Stop">
        <property name="_location" class="ptolemy.kernel.util.Location" value="[1150.0, 1035.0]">
        </property>
    </entity>
    <entity name="Receiver1" class="ptolemy.vergil.actor.lib.VisualModelReference">
        <property name="modelFileOrURL" class="ptolemy.actor.parameters.FilePortParameter" value="Receiver1.xml">
        </property>
        <property name="executionOnFiring" class="ptolemy.data.expr.StringParameter" value="run in a new thread">
        </property>
        <property name="lingerTime" class="ptolemy.data.expr.Parameter" value="100L">
        </property>
        <property name="spawnSeparateModels" class="ptolemy.data.expr.Parameter" value="false">
        </property>
        <property name="openOnFiring" class="ptolemy.data.expr.StringParameter" value="open in Vergil">
        </property>
        <property name="_location" class="ptolemy.kernel.util.Location" value="[1325.0, 1035.0]">
        </property>
    </entity>
</entity>
